__init__.py
helpers.py
scan.py
getFavicon-0.1.dist-info/METADATA
getFavicon-0.1.dist-info/WHEEL
getFavicon-0.1.dist-info/top_level.txt
getFavicon-0.1.dist-info/RECORD
