Metadata-Version: 2.1
Name: getFavicon
Version: 0.1
Summary: A Python library to fetch favicons from URLs
Home-page: https://github.com/talmkg/getFavicon
Author: Tim Afanasiev
Author-email: timbusinez@gmail.com
License: MIT
Classifier: Programming Language :: Python :: 3.1
Requires-Dist: fastapi (==0.100.1)
Requires-Dist: uvicorn[standard] (==0.23.2)
Requires-Dist: aioredis (==2.0.1)
Requires-Dist: requests-cache (==1.1.0)
Requires-Dist: install (==1.3.5)
Requires-Dist: tldextract (==3.4.4)
Requires-Dist: pydantic (==1.10.2)
Requires-Dist: pillow (==10.0.0)
Requires-Dist: aiohttp (==3.8.5)
Requires-Dist: asyncio (==3.4.3)
Requires-Dist: lxml (==4.9.3)
